setup.py
py_zmq_pipeline.egg-info/PKG-INFO
py_zmq_pipeline.egg-info/SOURCES.txt
py_zmq_pipeline.egg-info/dependency_links.txt
py_zmq_pipeline.egg-info/requires.txt
py_zmq_pipeline.egg-info/top_level.txt
zmqpipeline/__init__.py
zmqpipeline/collector.py
zmqpipeline/descriptors.py
zmqpipeline/distributor.py
zmqpipeline/helpers.py
zmqpipeline/task.py
zmqpipeline/version.py
zmqpipeline/worker.py
zmqpipeline/zhelpers.py
zmqpipeline/../VERSION
zmqpipeline/../description.txt
zmqpipeline/utils/__init__.py
zmqpipeline/utils/messages.py
zmqpipeline/utils/serializer.py
zmqpipeline/utils/shutdown.py